src/server.py
iflow_mcp_pdf_reader-1.0.0.dist-info/METADATA
iflow_mcp_pdf_reader-1.0.0.dist-info/WHEEL
iflow_mcp_pdf_reader-1.0.0.dist-info/entry_points.txt
iflow_mcp_pdf_reader-1.0.0.dist-info/RECORD
