Metadata-Version: 2.4
Name: iflow-mcp-pdf-reader
Version: 1.0.0
Summary: A Model Context Protocol (MCP) server that provides tools for reading and extracting text from PDF files
Project-URL: Homepage, https://github.com/iflow-mcp/pdf-reader-mcp-1
Project-URL: Repository, https://github.com/iflow-mcp/pdf-reader-mcp-1
Author-email: Philip Van de Walker <philip.vandewalker@gmail.com>
License: Apache-2.0
Requires-Python: >=3.11
Requires-Dist: mcp>=1.0.0
Requires-Dist: pypdf2>=3.0.0
Requires-Dist: requests>=2.31.0
